{"buildTime":"2021-11-17T07:44:31.361Z","sources":[{"id":"ComicK","name":"ComicK","author":"Nouun","desc":"Extension that scrapes comics from ComicK.fun.","website":"https://github.com/nouun/","contentRating":"ADULT","version":"0.1.0","icon":"icon.png","websiteBaseURL":"https://comick.fun"},{"id":"Zahard","name":"Zahard","author":"Nouun","desc":"Extension that scrapes manwha and webtoons from Zahard.top.","website":"https://github.com/nouun/","contentRating":"ADULT","version":"0.1.0","icon":"icon.png","websiteBaseURL":"https://zahard.top"}]}